Metadata-Version: 1.2
Name: hapdab
Version: 0.0.2
Summary: An library for managing and analyzing genotypes and haplotypes
Home-page: http://linkage.io
Author: Rob Schaefer
Author-email: rob@linkage.io
License: Copyright Linkage Analytics 2016-2018. Available under the MIT License
Project-URL: Documentation, http://linkage.io
Project-URL: Source, https://github.com/LinkageIO/HapDab
Project-URL: Tracker, https://github.com/LinkageIO/Minus80/HapDab
Keywords: data storage biology freeze
Platform: UNKNOWN
Classifier: Development Status :: 4 - Beta
Classifier: Intended Audience :: Developers
Classifier: Topic :: Software Development :: Build Tools
Classifier: License :: OSI Approved :: MIT License
Classifier: Programming Language :: Python :: 3
Classifier: Programming Language :: Python :: 3.6
Requires-Python: >=3.6
